{
  "project_info": {
    "project_number": "495954214507",
    "firebase_url": "https://habits-65054.firebaseio.com",
    "project_id": "habits-65054",
    "storage_bucket": "habits-65054.appspot.com"
  },
  "client": [
    {
      "client_info": {
        "mobilesdk_app_id": "1:495954214507:android:1a43a777c7543570073b2e",
        "android_client_info": {
          "package_name": "com.habits.app"
        }
      },
      "oauth_client": [
        {
          "client_id": "495954214507-q2p9kla8bkdd3gcig8aap60u2afgddrv.apps.googleusercontent.com",
          "client_type": 3
        }
      ],
      "api_key": [
        {
          "current_key": "AIzaSyBXEM-Br1Rhuudzkue6CSfe-J8fqr9P0mI"
        }
      ],
      "services": {
        "appinvite_service": {
          "other_platform_oauth_client": [
            {
              "client_id": "495954214507-q2p9kla8bkdd3gcig8aap60u2afgddrv.apps.googleusercontent.com",
              "client_type": 3
            }
          ]
        }
      }
    }
  ],
  "configuration_version": "1"
}